README.rst
nose_faulthandler.py
setup.py
nose_faulthandler.egg-info/PKG-INFO
nose_faulthandler.egg-info/SOURCES.txt
nose_faulthandler.egg-info/dependency_links.txt
nose_faulthandler.egg-info/entry_points.txt
nose_faulthandler.egg-info/not-zip-safe
nose_faulthandler.egg-info/requires.txt
nose_faulthandler.egg-info/top_level.txt